{
  "backend_name": "rembg",
  "inference_ms": 2914.1260999895167,
  "fallback_used": false,
  "fallback_reason": null,
  "mask_confidence": 0.9633796486012858,
  "purity_score": 0.9928689260604148,
  "support_suspected": false,
  "confidence": 0.9633796486012858,
  "segmentation_method": "rembg",
  "occupancy": 0.2734884982638889,
  "is_clipped": false,
  "support_removed": false,
  "support_area_ratio": 0.0,
  "border_touch_ratio": 0.0,
  "bottom_band_ratio": 0.20620316404832784,
  "bottom_span_ratio": 0.4199074074074074,
  "bottom_contact_ratio": 0.0,
  "bbox": {
    "x": 213,
    "y": 1236,
    "w": 1182,
    "h": 2569
  },
  "centroid": {
    "x": 836.467891830461,
    "y": 2507.88939081545
  },
  "fragment_count": 1,
  "largest_contour_ratio": 1.0,
  "solidity": 0.9714757042416592
}